KagglePipeline/KagglePipeline.py
KagglePipeline/Utility.py
KagglePipeline/__init__.py
KagglePipeline/augmentation/__init__.py
KagglePipeline/evaluation/__init__.py
KagglePipeline/exploration/__init__.py
KagglePipeline/exploration/table/CorrelationDiscoverer.py
KagglePipeline/exploration/table/NanDiscoverer.py
KagglePipeline/exploration/table/OutlierDiscoverer.py
KagglePipeline/exploration/table/Utility.py
KagglePipeline/exploration/table/Visuals.py
KagglePipeline/exploration/table/__init__.py
KagglePipeline/models/ModelBase.py
KagglePipeline/models/__init__.py
KagglePipeline/models/neural_networks/NeuralNetwork.py
KagglePipeline/models/neural_networks/__init__.py
KagglePipeline/models/neural_networks/cnn/InceptionCNN.py
KagglePipeline/models/neural_networks/cnn/SimpleCNN.py
KagglePipeline/models/neural_networks/cnn/__init__.py
KagglePipeline/models/neural_networks/mlp/SimpleMLP.py
KagglePipeline/models/neural_networks/mlp/__init__.py
KagglePipeline/preprocessing/__init__.py
KagglePipeline/preprocessing/cleanup/EncodingCleanup.py
KagglePipeline/preprocessing/cleanup/NanCleanup.py
KagglePipeline/preprocessing/cleanup/Utility.py
KagglePipeline/preprocessing/cleanup/__init__.py
KagglePipeline/preprocessing/feature_engineering/Utility.py
KagglePipeline/preprocessing/feature_engineering/__init__.py
KagglePipeline/preprocessing/feature_engineering/common.py
KagglePipeline/preprocessing/feature_selection/TreeSelector.py
KagglePipeline/preprocessing/feature_selection/__init__.py
KagglePipeline/rapid_deployment/MultipleModels.py
KagglePipeline/rapid_deployment/__init__.py
KagglePipeline/rapid_deployment/table/LinearModels.py
KagglePipeline/rapid_deployment/table/TreeModels.py
KagglePipeline/rapid_deployment/table/__init__.py
KagglePipeline/specialized/__init__.py
dj_kaggle_pipeline-1.0.8.dist-info/LICENSE
dj_kaggle_pipeline-1.0.8.dist-info/METADATA
dj_kaggle_pipeline-1.0.8.dist-info/WHEEL
dj_kaggle_pipeline-1.0.8.dist-info/top_level.txt
dj_kaggle_pipeline-1.0.8.dist-info/RECORD
